ouuid/DateTimeUuid.py
ouuid/DateUuid.py
ouuid/Uuid.py
ouuid/UuidError.py
ouuid/__init__.py
ouuid/__util.py
ouuid/test/__init__.py
ouuid/test/unit.py
ouuid-1.0.0.dist-info/LICENSE
ouuid-1.0.0.dist-info/METADATA
ouuid-1.0.0.dist-info/WHEEL
ouuid-1.0.0.dist-info/top_level.txt
ouuid-1.0.0.dist-info/RECORD
